musher/musher_python.cpython-38-x86_64-linux-gnu.so
musher/__init__.py
musher-0.0.4.dist-info/WHEEL
musher-0.0.4.dist-info/AUTHORS
musher-0.0.4.dist-info/LICENSE
musher-0.0.4.dist-info/RECORD
musher-0.0.4.dist-info/top_level.txt
musher-0.0.4.dist-info/METADATA
