Metadata-Version: 2.1
Name: musher
Version: 0.0.4
Summary: Simple musical key detection
Home-page: https://github.com/jmaldon1/Musher
Author: Joshua Maldonado, Brian Silver
Author-email: joshjm9915@gmail.com
License: MIT
Project-URL: Documentation, https://jmaldon1.github.io/Musher/index.html
Keywords: music,musical key detect,key detect,hpcp,song
Platform: UNKNOWN
Classifier: Development Status :: 5 - Production/Stable
Classifier: Topic :: Utilities
Classifier: Programming Language :: Python
Classifier: Programming Language :: Python :: 3
Classifier: Programming Language :: Python :: 3 :: Only
Classifier: Programming Language :: Python :: 3.5
Classifier: Programming Language :: Python :: 3.6
Classifier: Programming Language :: Python :: 3.7
Classifier: Programming Language :: Python :: 3.8
Classifier: Programming Language :: Python :: 3.9
Classifier: Intended Audience :: Developers
Classifier: Operating System :: POSIX :: Linux
Classifier: Operating System :: Unix
Classifier: Operating System :: MacOS
Classifier: Operating System :: Microsoft :: Windows
